{
    "0C925A9F-4B76-11ED-80F3-9C2DCDB4171C": {
        "User": "Lipcu",
        "Account": {
            "Bilibili": "https://space.bilibili.com/443938367",
            "QQ": "2827180486",
            "Youtube": "https://www.youtube.com/@lipcurinnn8217",
            "Discord": "lipcu_"
        },
        "Role": "Admin",
        "Status": "true"
    },
    "A89AFC8E-C706-DB1D-AEE6-D843AE6D87C8": {
        "User": "daongochuy2008",
        "Account": {
            "Bilibili": null,
            "QQ": null,
            "Youtube": "https://www.youtube.com/@daongochuy2008",
            "Discord": "daongochuy2008"
        },
        "Role": "Admin",
        "Status": "true"
    },
    "33444335-3133-4230-5747-474231334435": {
        "User": "daongochuy2008 - net269",
        "Account": {
            "Bilibili": null,
            "QQ": null,
            "Youtube": "https://www.youtube.com/@daongochuy2008",
            "Discord": "daongochuy2008"
        },
        "Role": "Admin2",
        "Status": "true"
    },
    "7B49EFD7-033D-11ED-80F2-9C2DCD01F50B": {
        "User": "strawbisclingy",
        "Account": {
            "Bilibili": null,
            "QQ": null,
            "Youtube": "https://www.youtube.com/channel/UCgUQDuFbcvhzovXhPhblVeA",
            "Discord": "strawbisclingy"
        },
        "Role": "User",
        "Status": "true"
    }
}
